aevopy/__init__.py
aevopy/aevo.py
aevopy/api.py
aevopy/exceptions.py
aevopy/models.py
aevopy-0.1.1.dist-info/LICENSE
aevopy-0.1.1.dist-info/METADATA
aevopy-0.1.1.dist-info/WHEEL
aevopy-0.1.1.dist-info/RECORD
