Metadata-Version: 2.1
Name: aevopy
Version: 0.1.1
Summary: Simple client for aevo.xyz API
Author: crjameson
Author-email: crjamesonxyz@proton.me
Requires-Python: >=3.11,<4.0
Classifier: Programming Language :: Python :: 3
Classifier: Programming Language :: Python :: 3.11
Requires-Dist: dacite (>=1.8.1,<2.0.0)
Requires-Dist: eip712-structs-ng (>=2.0.1,<3.0.0)
Requires-Dist: eth-account (>=0.10.0,<0.11.0)
Requires-Dist: python-dotenv (>=1.0.0,<2.0.0)
Requires-Dist: requests (>=2.31.0,<3.0.0)
Requires-Dist: typing-extensions (>=4.9.0,<5.0.0)
